FastAdder_16.v
//16位快速加法器
module FastAdder_16 (a, b, cin, s, cout, gin, pin, gout, pout);
    input [15:0] a, b;
    input cin, gin, pin;
    output [15:0] s;
    output cout, gout, pout;
    wire [15:0] g, p;
    wire [15:0] ctemp;
    
    assign g = a & b;//进位产生
    assign p = a | b;//进位传播

    //进位逻辑
    assign ctemp[0] = g[0] | (p[0] & cin);
    assign ctemp[1] = g[1] | (p[1] & g[0])
        |(p[1] & p[0] & cin);
    assign ctemp[2] = g[2] | (p[2] & g[1])
        | (p[2] & p[1] & g[0]) 
        | (p[2] & p[1] & p[0] & cin);
    assign ctemp[3] = g[3] | (p[3] & g[2])
        | (p[3] & p[2] & g[1])
        | (p[3] & p[2] & p[1] & g[0])
        | (p[3] & p[2] & p[1] & p[0] & cin);
    assign ctemp[4] = g[4] | (p[4] & g[3])
        | (p[4] & p[3] & g[2])
        | (p[4] & p[3] & p[2] & g[1])
        | (p[4] & p[3] & p[2] & p[1] & g[0])
        | (p[4] & p[3] & p[2] & p[1] & p[0] & cin);
    assign ctemp[5] = g[4] | (p[5] & g[4])
        | (p[5] & p[4] & g[3])
        | (p[5] & p[4] & p[3] & g[2])
        | (p[5] & p[4] & p[3] & p[2] & g[1])
        | (p[5] & p[4] & p[3] & p[2] & p[1] & g[0])
        | (p[5] & p[4] & p[3] & p[2] & p[1] & p[0] & cin);
    assign ctemp[6] = g[5] | (p[6] & g[5])
        | (p[6] & p[5] & g[4])
        | (p[6] & p[5] & p[4] & g[3])
        | (p[6] & p[5] & p[4] & p[3] & g[2])
        | (p[6] & p[5] & p[4] & p[3] & p[2] & g[1])
        | (p[6] & p[5] & p[4] & p[3] & p[2] & p[1] & g[0])
        | (p[6] & p[5] & p[4] & p[3] & p[2] & p[1] & p[0] & cin);
    assign ctemp[7] = g[6] | (p[7] & g[6])
        | (p[7] & p[6] & g[5])
        | (p[7] & p[6] & p[5] & g[4])
        | (p[7] & p[6] & p[5] & p[4] & g[3])
        | (p[7] & p[6] & p[5] & p[4] & p[3] & g[2])
        | (p[7] & p[6] & p[5] & p[4] & p[3] & p[2] & g[1])
        | (p[7] & p[6] & p[5] & p[4] & p[3] & p[2] & p[1] & g[0])
        | (p[7] & p[6] & p[5] & p[4] & p[3] & p[2] & p[1] & p[0] & cin);
    assign ctemp[8] = g[7] | (p[7] & g[7])
        | (p[8] & p[7] & g[6])
        | (p[8] & p[7] & p[6] & g[5])
        | (p[8] & p[7] & p[6] & p[5] & g[4])
        | (p[8] & p[7] & p[6] & p[5] & p[4] & g[3])
        | (p[8] & p[7] & p[6] & p[5] & p[4] & p[3] & g[2])
        | (p[8] & p[7] & p[6] & p[5] & p[4] & p[3] & p[2] & g[1])
        | (p[8] & p[7] & p[6] & p[5] & p[4] & p[3] & p[2] & p[1] & g[0])
        | (p[8] & p[7] & p[6] & p[5] & p[4] & p[3] & p[2] & p[1] & p[0] & cin);
    assign ctemp[9] = g[8] | (p[8] & g[8])
        | (p[9] & p[8] & g[7])
        | (p[9] & p[8] & p[7] & g[6])
        | (p[9] & p[8] & p[7] & p[6] & g[5])
        | (p[9] & p[8] & p[7] & p[6] & p[5] & g[4])
        | (p[9] & p[8] & p[7] & p[6] & p[5] & p[4] & g[3])
        | (p[9] & p[8] & p[7] & p[6] & p[5] & p[4] & p[3] & g[2])
        | (p[9] & p[8] & p[7] & p[6] & p[5] & p[4] & p[3] & p[2] & g[1])
        | (p[9] & p[8] & p[7] & p[6] & p[5] & p[4] & p[3] & p[2] & p[1] & g[0])
        | (p[9] & p[8] & p[7] & p[6] & p[5] & p[4] & p[3] & p[2] & p[1] & p[0] & cin);
    assign ctemp[10] = g[9] | (p[9] & g[9])
        | (p[10] & p[9] & g[8])
        | (p[10] & p[9] & p[8] & g[7])
        | (p[10] & p[9] & p[8] & p[7] & g[6])
        | (p[10] & p[9] & p[8] & p[7] & p[6] & g[5])
        | (p[10] & p[9] & p[8] & p[7] & p[6] & p[5] & g[4])
        | (p[10] & p[9] & p[8] & p[7] & p[6] & p[5] & p[4] & g[3])
        | (p[10] & p[9] & p[8] & p[7] & p[6] & p[5] & p[4] & p[3] & g[2])
        | (p[10] & p[9] & p[8] & p[7] & p[6] & p[5] & p[4] & p[3] & p[2] & g[1])
        | (p[10] & p[9] & p[8] & p[7] & p[6] & p[5] & p[4] & p[3] & p[2] & p[1] & g[0])
        | (p[10] & p[9] & p[8] & p[7] & p[6] & p[5] & p[4] & p[3] & p[2] & p[1] & p[0] & cin);
    assign ctemp[11] = g[10] | (p[10] & g[10])
        | (p[11] & p[10] & g[9])
        | (p[11] & p[10] & p[9] & g[8])
        | (p[11] & p[10] & p[9] & p[8] & g[7])
        | (p[11] & p[10] & p[9] & p[8] & p[7] & g[6])
        | (p[11] & p[10] & p[9] & p[8] & p[7] & p[6] & g[5])
        | (p[11] & p[10] & p[9] & p[8] & p[7] & p[6] & p[5] & g[4])
        | (p[11] & p[10] & p[9] & p[8] & p[7] & p[6] & p[5] & p[4] & g[3])
        | (p[11] & p[10] & p[9] & p[8] & p[7] & p[6] & p[5] & p[4] & p[3] & g[2])
        | (p[11] & p[10] & p[9] & p[8] & p[7] & p[6] & p[5] & p[4] & p[3] & p[2] & g[1])
        | (p[11] & p[10] & p[9] & p[8] & p[7] & p[6] & p[5] & p[4] & p[3] & p[2] & p[1] & g[0])
        | (p[11] & p[10] & p[9] & p[8] & p[7] & p[6] & p[5] & p[4] & p[3] & p[2] & p[1] & p[0] & cin);
    assign ctemp[12] = g[11] | (p[11] & g[11])
        | (p[12] & p[11] & g[10])
        | (p[12] & p[11] & p[10] & g[9])
        | (p[12] & p[11] & p[10] & p[9] & g[8])
        | (p[12] & p[11] & p[10] & p[9] & p[8] & g[7])
        | (p[12] & p[11] & p[10] & p[9] & p[8] & p[7] & g[6])
        | (p[12] & p[11] & p[10] & p[9] & p[8] & p[7] & p[6] & g[5])
        | (p[12] & p[11] & p[10] & p[9] & p[8] & p[7] & p[6] & p[5] & g[4])
        | (p[12] & p[11] & p[10] & p[9] & p[8] & p[7] & p[6] & p[5] & p[4] & g[3])
        | (p[12] & p[11] & p[10] & p[9] & p[8] & p[7] & p[6] & p[5] & p[4] & p[3] & g[2])
        | (p[12] & p[11] & p[10] & p[9] & p[8] & p[7] & p[6] & p[5] & p[4] & p[3] & p[2] & g[1])
        | (p[12] & p[11] & p[10] & p[9] & p[8] & p[7] & p[6] & p[5] & p[4] & p[3] & p[2] & p[1] & g[0])
        | (p[12] & p[11] & p[10] & p[9] & p[8] & p[7] & p[6] & p[5] & p[4] & p[3] & p[2] & p[1] & p[0] & cin);
    assign ctemp[13] = g[12] | (p[12] & g[12])
        | (p[13] & p[12] & g[11])
        | (p[13] & p[12] & p[11] & g[9])
        | (p[13] & p[12] & p[11] & p[10] & g[9])
        | (p[13] & p[12] & p[11] & p[10] & p[9] & g[8])
        | (p[13] & p[12] & p[11] & p[10] & p[9] & p[8] & g[7])
        | (p[13] & p[12] & p[11] & p[10] & p[9] & p[8] & p[7] & g[6])
        | (p[13] & p[12] & p[11] & p[10] & p[9] & p[8] & p[7] & p[6] & g[5])
        | (p[13] & p[12] & p[11] & p[10] & p[9] & p[8] & p[7] & p[6] & p[5] & g[4])
        | (p[13] & p[12] & p[11] & p[10] & p[9] & p[8] & p[7] & p[6] & p[5] & p[4] & g[3])
        | (p[13] & p[12] & p[11] & p[10] & p[9] & p[8] & p[7] & p[6] & p[5] & p[4] & p[3] & g[2])
        | (p[13] & p[12] & p[11] & p[10] & p[9] & p[8] & p[7] & p[6] & p[5] & p[4] & p[3] & p[2] & g[1])
        | (p[13] & p[12] & p[11] & p[10] & p[9] & p[8] & p[7] & p[6] & p[5] & p[4] & p[3] & p[2] & p[1] & g[0])
        | (p[13] & p[12] & p[11] & p[10] & p[9] & p[8] & p[7] & p[6] & p[5] & p[4] & p[3] & p[2] & p[1] & p[0] & cin);
    assign ctemp[14] = g[13] | (p[13] & g[13])
        | (p[14] & p[13] & g[12])
        | (p[14] & p[13] & p[12] & g[11])
        | (p[14] & p[13] & p[12] & p[11] & g[9])
        | (p[14] & p[13] & p[12] & p[11] & p[10] & g[9])
        | (p[14] & p[13] & p[12] & p[11] & p[10] & p[9] & g[8])
        | (p[14] & p[13] & p[12] & p[11] & p[10] & p[9] & p[8] & g[7])
        | (p[14] & p[13] & p[12] & p[11] & p[10] & p[9] & p[8] & p[7] & g[6])
        | (p[14] & p[13] & p[12] & p[11] & p[10] & p[9] & p[8] & p[7] & p[6] & g[5])
        | (p[14] & p[13] & p[12] & p[11] & p[10] & p[9] & p[8] & p[7] & p[6] & p[5] & g[4])
        | (p[14] & p[13] & p[12] & p[11] & p[10] & p[9] & p[8] & p[7] & p[6] & p[5] & p[4] & g[3])
        | (p[14] & p[13] & p[12] & p[11] & p[10] & p[9] & p[8] & p[7] & p[6] & p[5] & p[4] & p[3] & g[2])
        | (p[14] & p[13] & p[12] & p[11] & p[10] & p[9] & p[8] & p[7] & p[6] & p[5] & p[4] & p[3] & p[2] & g[1])
        | (p[14] & p[13] & p[12] & p[11] & p[10] & p[9] & p[8] & p[7] & p[6] & p[5] & p[4] & p[3] & p[2] & p[1] & g[0])
        | (p[14] & p[13] & p[12] & p[11] & p[10] & p[9] & p[8] & p[7] & p[6] & p[5] & p[4] & p[3] & p[2] & p[1] & p[0] & cin);
    assign ctemp[15] = g[14] | (p[14] & g[14])
        | (p[15] & p[14] & p[13] & g[12])
        | (p[15] & p[14] & p[13] & p[12] & g[11])
        | (p[15] & p[14] & p[13] & p[12] & p[11] & g[9])
        | (p[15] & p[14] & p[13] & p[12] & p[11] & p[10] & g[9])
        | (p[15] & p[14] & p[13] & p[12] & p[11] & p[10] & p[9] & g[8])
        | (p[15] & p[14] & p[13] & p[12] & p[11] & p[10] & p[9] & p[8] & g[7])
        | (p[15] & p[14] & p[13] & p[12] & p[11] & p[10] & p[9] & p[8] & p[7] & g[6])
        | (p[15] & p[14] & p[13] & p[12] & p[11] & p[10] & p[9] & p[8] & p[7] & p[6] & g[5])
        | (p[15] & p[14] & p[13] & p[12] & p[11] & p[10] & p[9] & p[8] & p[7] & p[6] & p[5] & g[4])
        | (p[15] & p[14] & p[13] & p[12] & p[11] & p[10] & p[9] & p[8] & p[7] & p[6] & p[5] & p[4] & g[3])
        | (p[15] & p[14] & p[13] & p[12] & p[11] & p[10] & p[9] & p[8] & p[7] & p[6] & p[5] & p[4] & p[3] & g[2])
        | (p[15] & p[14] & p[13] & p[12] & p[11] & p[10] & p[9] & p[8] & p[7] & p[6] & p[5] & p[4] & p[3] & p[2] & g[1])
        | (p[15] & p[14] & p[13] & p[12] & p[11] & p[10] & p[9] & p[8] & p[7] & p[6] & p[5] & p[4] & p[3] & p[2] & p[1] & g[0])
        | (p[15] & p[14] & p[13] & p[12] & p[11] & p[10] & p[9] & p[8] & p[7] & p[6] & p[5] & p[4] & p[3] & p[2] & p[1] & p[0] & cin);

    //和输出
    assign s[0] = a[0] ^ b[0] ^ cin;
    assign s[1] = a[1] ^ b[1] ^ ctemp[0];
    assign s[2] = a[2] ^ b[2] ^ ctemp[1];
    assign s[3] = a[3] ^ b[3] ^ ctemp[2];
    assign s[4] = a[4] ^ b[4] ^ ctemp[3];
    assign s[5] = a[5] ^ b[5] ^ ctemp[4];
    assign s[6] = a[6] ^ b[6] ^ ctemp[5];
    assign s[7] = a[7] ^ b[7] ^ ctemp[6];
    assign s[8] = a[8] ^ b[8] ^ ctemp[7];
    assign s[9] = a[9] ^ b[9] ^ ctemp[8];
    assign s[10] = a[10] ^ b[10] ^ ctemp[9];
    assign s[11] = a[11] ^ b[11] ^ ctemp[10];
    assign s[12] = a[12] ^ b[12] ^ ctemp[11];
    assign s[13] = a[13] ^ b[13] ^ ctemp[12];
    assign s[14] = a[14] ^ b[14] ^ ctemp[13];
    assign s[15] = a[15] ^ b[15] ^ ctemp[14];

    //进位产生、传播信号输出
    assign gout = g[15];
    assign pout = p[15];
endmodule

Adder_32.v
//32位加法器
`include "FastAdder_16.v"

module Adder_32 (a, b, sub, s, overflow, zeroflag);
    input [31:0] a, b;
    input sub;
    output [31:0] s;
    output overflow;
    output zeroflag;
    wire gtemp, ptemp, ctemp;

    //2个16位快速加法器串联
    FastAdder_16 FastAdder_16_0 (.a(a[15:0]), .b(b[15:0]), .cin(sub),
            .s(s[15:0]),.cout(ctemp), .gin(), .pin(), .gout(gtemp), .pout(ptemp));
    FastAdder_16 FastAdder_16_1 (.a(a[31:16]), .b(b[31:16]), .cin(ctemp),
            .s(s[31:16]), .cout(overflow), .gin(gtemp), .pin(ptemp), .gout(), .pout());
    
    //零标志寄存器
    assign zeroflag = (s==0)?1'b0:1'b1;
endmodule

test_alu.v
`timescale 1ns/1ps
`include "Adder_32.v"

module test_alu() ;

Adder_32 uut(.a(a), .b(b), .sub(zero), .s(s), .overflow(overflow));

reg [31:0] a ;
reg [31:0]b ;
wire [31:0]s ;
wire overflow ;
wire zero ;

integer i; // Loop counter
integer expected_sum ;
integer expected_overflow ;

assign zero = 0 ;

initial begin
    $dumpfile ("test_alu.vcd") ;
    $dumpvars (0 , test_alu) ;

    // Randomly test for 1000 iterations
    for (i = 0; i < 10; i = i + 1) begin
      // Generate random 32-bit values for a and b
      a = $random;
      b = $random;

      #10; // Delay to allow module to settle

      // Expected output based on addition operation
      expected_sum = a + b;
      expected_overflow = (a > 2**31 - b) || (b > 2**31 - a);

      #10;

      // Check if adder output matches expected values
      if (s!==expected_sum) $display("ERROR: Sum mismatch for %dth test case", i);
      if (overflow!==expected_overflow) $display("ERROR: Overflow mismatch for %dth test case", i);

      // Print test case results
      $display("Test case %d passed: a=%d, b=%d, s=%d, overflow=%d", i, a, b, s, overflow);
    end
    $finish; // Simulation stops after all test cases run
  end

endmodule

test_alu.vcd
$date
	Mon Dec 18 19:50:49 2023
$end
$version
	Icarus Verilog
$end
$timescale
	1ps
$end
$scope module test_alu $end
$var wire 1 ! overflow $end
$var wire 1 " zero $end
$var wire 32 # s [31:0] $end
$var reg 32 $ a [31:0] $end
$var reg 32 % b [31:0] $end
$var integer 32 & expected_overflow [31:0] $end
$var integer 32 ' expected_sum [31:0] $end
$var integer 32 ( i [31:0] $end
$scope module uut $end
$var wire 32 ) a [31:0] $end
$var wire 32 * b [31:0] $end
$var wire 1 + ctemp $end
$var wire 1 ! overflow $end
$var wire 1 " sub $end
$var wire 1 , zeroflag $end
$var wire 32 - s [31:0] $end
$var wire 1 . ptemp $end
$var wire 1 / gtemp $end
$scope module FastAdder_16_0 $end
$var wire 16 0 a [15:0] $end
$var wire 16 1 b [15:0] $end
$var wire 1 " cin $end
$var wire 1 + cout $end
$var wire 16 2 g [15:0] $end
$var wire 1 3 gin $end
$var wire 16 4 p [15:0] $end
$var wire 1 5 pin $end
$var wire 16 6 s [15:0] $end
$var wire 1 . pout $end
$var wire 1 / gout $end
$var wire 16 7 ctemp [15:0] $end
$upscope $end
$scope module FastAdder_16_1 $end
$var wire 16 8 a [15:0] $end
$var wire 16 9 b [15:0] $end
$var wire 1 + cin $end
$var wire 1 ! cout $end
$var wire 16 : g [15:0] $end
$var wire 1 / gin $end
$var wire 16 ; p [15:0] $end
$var wire 1 . pin $end
$var wire 16 < s [15:0] $end
$var wire 1 = pout $end
$var wire 1 > gout $end
$var wire 16 ? ctemp [15:0] $end
$upscope $end
$upscope $end
$upscope $end
$enddefinitions $end
$comment Show the parameter values. $end
$dumpall
$end
#0
$dumpvars
b1 ?
0>
1=
b110100101001111x <
b1101001010011101 ;
b1 :
b1100000010001001 9
b1001000010101 8
b111100000000000 7
b1001101110100101 6
z5
b111111110100101 4
z3
b1010000000000 2
b101111010000001 1
b11010100100100 0
0/
0.
b110100101001111x1001101110100101 -
1,
z+
b11000000100010010101111010000001 *
b10010000101010011010100100100 )
b0 (
bx '
bx &
b11000000100010010101111010000001 %
b10010000101010011010100100100 $
b110100101001111x1001101110100101 #
0"
z!
$end
#10000
b1 &
b11010010100111101001001110100101 '
#20000
b1010110000000011 7
b1101100001101100 6
b100000000 ?
b1101110111010x1101100001101100 #
b1101110111010x1101100001101100 -
b1101110111010x <
1.
1>
b101011000000001 2
b1101011001101011 4
b1000000010000000 :
b1011010111110100 ;
b101011001100011 1
b1011000111110000 9
b1101011000001001 0
b1000010010000100 8
b10110001111100000101011001100011 %
b10110001111100000101011001100011 *
b10000100100001001101011000001001 $
b10000100100001001101011000001001 )
b1 (
#30000
b0 &
b110110011101010010110001101100 '
#40000
b1111001000001101 7
b11010011010 6
b110111111111 ?
b10110111001100x0000011010011010 #
b10110111001100x0000011010011010 -
b10110111001100x <
0>
0=
b1100100001101 2
b1111101110001101 4
b11010011001 :
b100011011111111 ;
b1001100110001101 1
b100011011011111 9
b111101100001101 0
b11010111001 8
b1000110110111111001100110001101 %
b1000110110111111001100110001101 *
b110101110010111101100001101 $
b110101110010111101100001101 )
b10 (
#50000
b1001101100110010001010010011010 '
#60000
b0 7
b1101011001110111 6
b11x ?
b111011111110xx1101011001110111 #
b111011111110xx1101011001110111 -
b111011111110xx <
1>
1=
b0 2
b1101011001110111 4
b1000000000000010 :
b1011101111110111 ;
b101001000010010 1
b1000100100110111 9
b1000010001100101 0
b1011001011000010 8
b10001001001101110101001000010010 %
b10001001001101110101001000010010 *
b10110010110000101000010001100101 $
b10110010110000101000010001100101 )
b11 (
#70000
b111011111110011101011001110111 '
#80000
b1000111000000001 7
b11001000001110 6
b111110111 ?
b1011100101x0011001000001110 #
b1011100101x0011001000001110 -
b1011100101x <
1/
0>
0=
b1100000100000001 2
b1110111100001101 4
b11010011 :
b11011110111 ;
b1100110100001101 1
b11011010111 9
b1110001100000001 0
b11110011 8
b110110101111100110100001101 %
b110110101111100110100001101 *
b111100111110001100000001 $
b111100111110001100000001 )
b100 (
#90000
b111110010111011000000001110 '
#100000
b11110000001111 ?
b1000001001111100 7
b11100010110011 6
b10111011011000x0011100010110011 #
b10111011011000x0011100010110011 -
b10111011011000x <
b1100000100110100 2
b1111110101111111 4
b1101000000001 :
b11111110101111 ;
b1100110100111101 1
b1111010001101 9
b1111000101110110 0
b11101100100011 8
b11110100011011100110100111101 %
b11110100011011100110100111101 *
b111011001000111111000101110110 $
b111011001000111111000101110110 )
b101 (
#110000
b1011001101100011011111010110011 '
#120000
b1110111100001100 7
b111111001111001 6
b100011001111110x ?
b101001000000xx0111111001111001 #
b101001000000xx0111111001111001 -
b101001000000xx <
0/
b101011110001100 2
b1111011111101101 4
b100011000000100 :
b111011011111101 ;
b1111011110001100 1
b100011000101101 9
b101011111101101 0
b111011011010100 8
b1000110001011011111011110001100 %
b1000110001011011111011110001100 *
b1110110110101000101011111101101 $
b1110110110101000101011111101101 )
b110 (
#130000
b1 &
b10111101000000100100111101111001 '
#140000
b100000110000000 7
b100111000111111 6
b1111111111111111 ?
b11000000011010x0100111000111111 #
b11000000011010x0100111000111111 -
b11000000011010x <
1=
b10000011000000 2
b1110110111111111 4
b110000000110101 :
b1111111111111111 ;
b10010011000110 1
b1110001100110111 9
b1110100111111001 0
b111110011111101 8
b11100011001101110010010011000110 %
b11100011001101110010010011000110 *
b1111100111111011110100111111001 $
b1111100111111011110100111111001 )
b111 (
#150000
b1100000001101010000111010111111 '
#160000
b100000000 7
b1000011111110111 ?
b101010001101111 6
b1110000000101x0101010001101111 #
b1110000000101x0101010001101111 -
b1110000000101x <
1/
1>
b1000000010000000 2
b1101011011101111 4
b1100000000010011 :
b1111011111110111 ;
b1101001010101010 1
b1101010100010011 9
b1000010011000101 0
b1110001011110111 8
b11010101000100111101001010101010 %
b11010101000100111101001010101010 *
b11100010111101111000010011000101 $
b11100010111101111000010011000101 )
b1000 (
#170000
b10111000000010110101011101101111 '
#180000
b1110011111000111 7
b100101000011100 6
b111001111111111x ?
b110100000xx0100101000011100 #
b110100000xx0100101000011100 -
b110100000xx <
0/
0>
b111001001100101 2
b1111011111110111 4
b11001010000010 :
b1111101111111111 ;
b111001001110111 1
b1011101111010010 9
b1111011111100101 0
b111001010101111 8
b10111011110100100111001001110111 %
b10111011110100100111001001110111 *
b1110010101011111111011111100101 $
b1110010101011111111011111100101 )
b1001 (
#190000
b101110100000100110101001011100 '
#200000
b1010 (
